{
  "club_id": "halifax-trail-runners-website",
  "source_url": "https://halifaxtrailrunnersclub.blogspot.com",
  "checked_at": "2026-04-28T12:10:08Z",
  "content_hash": "ac9e7d0b68dfc4ed2a697ec7db79ea2e6995dc2b0b1ea01b3da057521d5b0982",
  "html_excerpt": "<!DOCTYPE html>\n<html class='v2' dir='ltr' xmlns='http://www.w3.org/1999/xhtml' xmlns:b='http://www.google.com/2005/gml/b' xmlns:data='http://www.google.com/2005/gml/data' xmlns:expr='http://www.google.com/2005/gml/expr'>\n<head>\n<link href='https://www.blogger.com/static/v1/widgets/335934321-css_bundle_v2.css' rel='stylesheet' type='text/css'/>\n<meta content='IE=EmulateIE7' http-equiv='X-UA-Compatible'/>\n<meta content='width=1100' name='viewport'/>\n<meta content='text/html; charset=UTF-8' http-equiv='Content-Type'/>\n<meta content='blogger' name='generator'/>\n<link href='https://halifaxtrailrunnersclub.blogspot.com/favicon.ico' rel='icon' type='image/x-icon'/>\n<link href='http://halifaxtrailrunnersclub.blogspot.com/' rel='canonical'/>\n<link rel=\"alternate\" type=\"application/atom+xml\" title=\"Halifax Trail Runners Club - Atom\" href=\"https://halifaxtrailrunnersclub.blogspot.com/feeds/posts/default\" />\n<link rel=\"alternate\" type=\"application/rss+xml\" title=\"Halifax Trail Runners Club - RSS\" href=\"https://halifaxtrailrunnersclub.blogspot.com/feeds/posts/default?alt=rss\" />\n<link rel=\"service.post\" type=\"application/atom+xml\" title=\"Halifax Trail Runners Club - Atom\" href=\"https://www.blogger.com/feeds/7655259799696189673/posts/default\" />\n<link rel=\"me\" href=\"https://www.blogger.com/profile/12397811451469461423\" />\n<!--Can't find substitution for tag [blog.ieCssRetrofitLinks]-->\n<meta content='http://halifaxtrailrunnersclub.blogspot.com/' property='og:url'/>\n<meta content='Halifax Trail Runners Club' property='og:title'/>\n<meta content='' property='og:description'/>\n<title>Halifax Trail Runners Club</title>\n<style id='page-skin-1' type='text/css'><!--\n/*\n-----------------------------------------------\nBlogger Template Style\nName:     Simple\nDesigner: Josh Peterson\nURL:      www.noaesthetic.com\n----------------------------------------------- */\n/* Variable definitions\n====================\n<Variable name=\"keycolor\" description=\"Main Color\" type=\"color\" default=\"#66bbdd\"/>\n<Group description=\"Page Text\" selector=\"body\">\n<Variable name=\"body.font\" description=\"Font\" type=\"font\"\ndefault=\"normal normal 12px Arial, Tahoma, Helvetica, FreeSans, sans-serif\"/>\n<Variable name=\"body.text.color\" description=\"Text Color\" type=\"color\" default=\"#222222\"/>\n</Group>\n<Group description=\"Backgrounds\" selector=\".body-fauxcolumns-outer\">\n<Variable name=\"body.background.color\" description=\"Outer Background\" type=\"color\" default=\"#66bbdd\"/>\n<Variable name=\"content.background.color\" description=\"Main Background\" type=\"color\" default=\"#ffffff\"\n/>\n<Variable name=\"header.background.color\" description=\"Header Background\" type=\"color\" default=\"transparent\"\n/>\n</Group>\n<Group description=\"Links\" selector=\".main-outer\">\n<Variable name=\"link.color\" description=\"Link Color\" type=\"color\" default=\"#2288bb\"/>\n<Variable name=\"link.visited.color\" description=\"Visited Color\" type=\"color\" default=\"#888888\"/>\n<Variable name=\"link.hover.color\" description=\"Hover Color\" type=\"color\" default=\"#33aaff\"/>\n</Group>\n<Group description=\"Blog Title\" selector=\".header h1\">\n<Variable name=\"header.font\" description=\"Font\" type=\"font\"\ndefault=\"normal normal 60px Arial, Tahoma, Helvetica, FreeSans, sans-serif\"/>\n<Variable name=\"header.text.color\" description=\"Title Color\" type=\"color\" default=\"#3399bb\" />\n</Group>\n<Group description=\"Blog Description\" selector=\".header .description\">\n<Variable name=\"description.text.color\" description=\"Description Color\" type=\"color\"\ndefault=\"#777777\" />\n</Group>\n<Group description=\"Tabs Text\" selector=\".tabs-inner .widget li a\">\n<Variable name=\"tabs.font\" description=\"Font\" type=\"font\"\ndefault=\"normal normal 14px Arial, Tahoma, Helvetica, FreeSans, sans-serif\"/>\n<Variable name=\"tabs.text.color\" description=\"Text Color\" type=\"color\" default=\"#999999\"/>\n<Variable name=\"tabs.selected.text.color\" description=\"Selected Color\" type=\"color\" default=\"#000000\"/>\n</Group>\n<Group description=\"Tabs Background\" selector=\".tabs-outer .PageList\">\n<Variable name=\"tabs.background.color\" description=\"Background Color\" type=\"color\" default=\"#f5f5f5\"/>\n<Variable name=\"tabs.selected.background.color\" description=\"Selected Color\" type=\"color\" default=\"#eeeeee\"\n/>\n</Group>\n<Group description=\"Post Title\" selector=\"h3.post-title, .comments h4\">\n<Variable name=\"post.title.font\" description=\"Font\" type=\"font\"\ndefault=\"normal normal 22px Arial, Tahoma, Helvetica, FreeSans, sans-serif\"/>\n</Group>\n<Group description=\"Date Header\" selector=\".date-header\">\n<Variable name=\"date.header.color\" description=\"Text Color\" type=\"color\"\ndefault=\"#402813\"/>\n<Variable name=\"date.header.background.color\" description=\"Background Color\" type=\"color\"\ndefault=\"transparent\"/>\n</Group>\n<Group description=\"Post Footer\" selector=\".post-footer\">\n<Variable name=\"post.footer.text.color\" description=\"Text Color\" type=\"color\" default=\"#666666\"/>\n<Variable name=\"post.footer.background.color\" description=\"Background Color\" type=\"color\"\ndefault=\"#f9f9f9\"/>\n<Variable name=\"post.footer.border.color\" description=\"Shadow Color\" type=\"color\" default=\"#eeeeee\"/>\n</Group>\n<Group description=\"Gadgets\" selector=\"h2\">\n<Variable name=\"widget.title.font\" description=\"Title Font\" type=\"font\"\ndefault=\"normal bold 11px Arial, Tahoma, Helvetica, FreeSans, sans-serif\"/>\n<Variable name=\"widget.title.text.color\" description=\"Title Color\" type=\"color\" default=\"#000000\"/>\n<Variable name=\"widget.alternate.text.color\" description=\"Alternate Color\" type=\"color\" default=\"#999999\"\n/>\n</Group>\n<Group description=\"Images\" selector=\".main-inner\">\n<Variable name=\"image.background.color\" description=\"Background Color\" type=\"color\" default=\"#ffffff\"/>\n<Variable name=\"image.border.color\" description=\"Border Color\" type=\"color\" default=\"#eeeeee\"/>\n<Variable name=\"image.text.color\" description=\"Caption Text Color\" type=\"color\" default=\"#402813\"\n/>\n</Group>\n<Group description=\"Accents\" selector=\".content-inner\">\n<Variable name=\"body.rule.color\" description=\"Separator Line Color\" type=\"color\" default=\"#eeeeee\"/>\n<Variable name=\"tabs.border.color\" description=\"Tabs Border Color\" type=\"color\" default=\"transparent\"\n/>\n</Group>\n<Variable name=\"body.background\" description=\"Body Background\" type=\"background\"\ncolor=\"#616b2d\" default=\"$(color) none repeat scroll top left\"/>\n<Variable name=\"body.background.override\" description=\"Body Background Override\" type=\"string\" default=\"\"/>\n<Variable name=\"body.background.gradient.cap\" description=\"Body Gradient Cap\" type=\"url\"\ndefault=\"url(http://www.blogblog.com/1kt/simple/gradients_light.png)\"\n/>\n<Variable name=\"body.background.gradient.tile\" description=\"Body Gradient Tile\" type=\"url\"\ndefault=\"url(http://www.blogblog.com/1kt/simple/body_gradient_tile_light.png)\"\n/>\n<Variable name=\"content.background.color.selector\" description=\"Content Background Color Selector\" type=\"string\"\ndefault=\".content-inner\"/>\n<Variable name=\"content.padding\" description=\"Content Padding\" type=\"length\" default=\"10px\"/>\n<Variable name=\"content.padding.horizontal\" description=\"Content Horizontal Padding\" type=\"length\"\ndefault=\"10px\"/>\n<Variable name=\"content.shadow.spread\" description=\"Content Shadow Spread\" type=\"length\" default=\"40px\"/>\n<Variable name=\"content.shadow.spread.webkit\" description=\"Content Shadow Spread (WebKit)\" type=\"length\" default=\"5px\"\n/>\n<Variable name=\"content.shadow.spread.ie\" description=\"Content Shadow Spread (IE)\" type=\"length\" default=\"10px\"\n/>\n<Variable name=\"main.border.width\" description=\"Main Border Width\" type=\"length\" default=\"0\"/>\n<Variable name=\"header.background.gradient\" description=\"Header Gradient\" type=\"url\" default=\"none\"/>\n<Variable name=\"header.shadow.offset.left\" description=\"Header Shadow Offset Left\" type=\"length\" default=\"-1px\"\n/>\n<Variable name=\"header.shadow.offset.top\" description=\"Header Shadow Offset Top\" type=\"length\" default=\"-1px\"\n/>\n<Variable name=\"header.shadow.spread\" description=\"Header Shadow Spread\" type=\"length\" default=\"1px\"/>\n<Variable name=\"header.padding\" description=\"Header Padding\" type=\"length\" default=\"30px\"/>\n<Variable name=\"header.border.size\" description=\"Header Border Size\" type=\"length\" default=\"1px\"/>\n<Variable name=\"header.bottom.border.size\" description=\"Header Bottom Border Size\" type=\"length\"\ndefault=\"1px\"/>\n<Variable name=\"header.border.horizontalsize\" description=\"Header Horizontal Border Size\" type=\"length\" default=\"0\"\n/>\n<Variable name=\"description.text.size\" description=\"Description Text Size\" type=\"string\" default=\"140%\"/>\n<Variable name=\"tabs.margin.top\" description=\"Tabs Margin Top\" type=\"length\" default=\"0\" />\n<Variable name=\"tabs.margin.side\" description=\"Tabs Side Margin\" type=\"length\" default=\"30px\" />\n<Variable name=\"tabs.background.gradient\" description=\"Tabs Background Gradient\" type=\"url\"\ndefault=\"url(http://www.blogblog.com/1kt/simple/gradients_light.png)\"\n/>\n<Variable name=\"tabs.border.width\" description=\"Tabs Border Width\" type=\"length\" default=\"1px\"/>\n<Variable name=\"tabs.bevel.border.width\" description=\"Tabs Bevel Border Width\" type=\"length\" default=\"1px\"/>\n<Variable name=\"date.header.padding\" description=\"Date Header Padding\" type=\"string\" default=\"inherit\"/>\n<Variable name=\"date.header.letterspacing\" description=\"Date Header Letter Spacing\" type=\"string\" default=\"inherit\"\n/>\n<Variable name=\"date.header.margin\" description=\"Date Header Margin\" type=\"string\" default=\"inherit\"/>\n<Variable name=\"post.margin.bottom\" description=\"Post Bottom Margin\" type=\"length\" default=\"25px\"/>\n<Variable name=\"image.border.small.size\" description=\"Image Border Small Size\" type=\"length\" default=\"2px\"/>\n<Variable name=\"image.border.large.size\" description=\"Image Border Large Size\" type=\"length\" default=\"5px\"/>\n<Variable name=\"page.width.selector\" description=\"Page Width Selector\" type=\"string\" default=\".region-inner\"\n/>\n<Variable name=\"page.width\" description=\"Page Width\" type=\"string\" default=\"auto\"/>\n<Variable name=\"main.section.margin\" description=\"Main Section Margin\" type=\"length\" default=\"15px\"/>\n<Variable name=\"main.padding\" descripti"
}